udp_client/__init__.py
udp_client/udp_client.py
udp_client_package-0.1.0.dist-info/LICENSE
udp_client_package-0.1.0.dist-info/METADATA
udp_client_package-0.1.0.dist-info/WHEEL
udp_client_package-0.1.0.dist-info/entry_points.txt
udp_client_package-0.1.0.dist-info/top_level.txt
udp_client_package-0.1.0.dist-info/RECORD
