Metadata-Version: 2.1
Name: udp-client-package
Version: 0.1.0
Summary: 一个简单的UDP客户端API
Home-page: https://你的项目网址
Author: lhb
Author-email: spike.edjet@gmail.com
License: UNKNOWN
Platform: UNKNOWN
Classifier: Programming Language :: Python :: 3
Classifier: Operating System :: OS Independent
Requires-Python: >=3.6
Requires-Dist: PySide6
